squidlayer/__init__.py
squidlayer-0.0.1.dist-info/METADATA
squidlayer-0.0.1.dist-info/WHEEL
squidlayer-0.0.1.dist-info/top_level.txt
squidlayer-0.0.1.dist-info/RECORD
